QBenchAnalyzer/__init__.py
QBenchAnalyzer/circuit_analyzer.py
QBenchAnalyzer/literal.py
QBenchAnalyzer/metrics_generator.py
QBenchAnalyzer/CircuitGenerator/__init__.py
QBenchAnalyzer/CircuitGenerator/generator_interface.py
QBenchAnalyzer/CircuitGenerator/qwalk_generator.py
QBenchAnalyzer/CircuitGenerator/static_generator.py
qbenchanalyzer-0.0.4.dist-info/licenses/LICENSE.md
qbenchanalyzer-0.0.4.dist-info/METADATA
qbenchanalyzer-0.0.4.dist-info/WHEEL
qbenchanalyzer-0.0.4.dist-info/top_level.txt
qbenchanalyzer-0.0.4.dist-info/RECORD
